{"homepage":"https://github.com/guzba/curly","versions":[{"nimble":{"author":"Ryan Oldenburg","backend":"c","binDir":".","description":"An easy to use and efficient thread-ready HTTP client","license":"MIT","requires":[{"name":"nim","range":">= 1.6.10"},{"name":"libcurl","range":">= 1.0.0"},{"name":"zippy","range":">= 0.10.6"},{"name":"webby","range":">= 0.1.7"}],"specialVersion":"1.0.0","srcDir":"src"},"source":{"url":"https://github.com/guzba/curly","rev":"0fbe9b2f6cb39551f9ddefdb99c91414193c01c3","date":"2024-01-20T15:06:15-06:00","path":"/nix/store/cykd3rp2hrg2prlbl3l425krb93h17wk-curly","sha256":"0bpyjn0h46fd56fj3njb7z7iahdzz30dxj5f5kwk0v8gdy061bcb","fetchLFS":false,"fetchSubmodules":true,"deepClone":false,"leaveDotGit":false,"method":"git"},"version":"1.0.0"},{"nimble":{"author":"Ryan Oldenburg","backend":"c","binDir":".","description":"Makes using libcurl efficiently easy","license":"MIT","requires":[{"name":"nim","range":">= 1.6.10"},{"name":"libcurl","range":">= 1.0.0"},{"name":"zippy","range":">= 0.10.6"},{"name":"webby","range":">= 0.1.7"}],"specialVersion":"0.1.13","srcDir":"src"},"source":{"url":"https://github.com/guzba/curly","rev":"a6b9e15e12b12ad1395b321eea5e476d9b6d3a14","date":"2024-01-16T12:01:22-06:00","path":"/nix/store/iqnmxm5qabk3bsn2w9z87nybzzsqmm0g-curly","sha256":"07f073qybk7h04029lncp0vf3jdagpsdc9ssi33wmz5gakz9426v","fetchLFS":false,"fetchSubmodules":true,"deepClone":false,"leaveDotGit":false,"method":"git"},"version":"0.1.13"},{"nimble":{"author":"Ryan Oldenburg","backend":"c","binDir":".","description":"Makes using libcurl efficiently easy","license":"MIT","requires":[{"name":"nim","range":">= 1.6.10"},{"name":"libcurl","range":">= 1.0.0"},{"name":"zippy","range":">= 0.10.6"},{"name":"webby","range":">= 0.1.7"}],"specialVersion":"0.1.12","srcDir":"src"},"source":{"url":"https://github.com/guzba/curly","rev":"8598ad5c3b0c1eb65b5e3017688a2fa31a34225f","date":"2023-08-29T14:09:43-05:00","path":"/nix/store/gvyy2c566q9bwlv620h0749x0p2sjjbh-curly","sha256":"1iganfj3hwgysxih98c1kpxqf1q8wnw5h3xmirmn8nn0kx5cdan3","fetchLFS":false,"fetchSubmodules":true,"deepClone":false,"leaveDotGit":false,"method":"git"},"version":"0.1.12"},{"nimble":{"author":"Ryan Oldenburg","backend":"c","binDir":".","description":"Makes using libcurl efficiently easy","license":"MIT","requires":[{"name":"nim","range":">= 1.6.10"},{"name":"libcurl","range":">= 1.0.0"},{"name":"zippy","range":">= 0.10.6"},{"name":"waterpark","range":">= 0.1.4"},{"name":"webby","range":">= 0.1.7"}],"specialVersion":"0.1.11","srcDir":"src"},"source":{"url":"https://github.com/guzba/curly","rev":"ecffdf5c09929a044c49c1e52624d130c8f4825c","date":"2023-08-17T23:39:08-05:00","path":"/nix/store/vaccvh8kmjrgi45y7i23c96l9z9ng2rs-curly","sha256":"031425fdqdjqqascazv96mgxz70il4c5j08zmi1z4zszhcp666x6","fetchLFS":false,"fetchSubmodules":true,"deepClone":false,"leaveDotGit":false,"method":"git"},"version":"0.1.11"},{"nimble":{"author":"Ryan Oldenburg","backend":"c","binDir":".","description":"Makes using libcurl efficiently easy","license":"MIT","requires":[{"name":"nim","range":">= 1.6.10"},{"name":"libcurl","range":">= 1.0.0"},{"name":"zippy","range":">= 0.10.6"},{"name":"waterpark","range":">= 0.1.3"},{"name":"webby","range":">= 0.1.7"}],"specialVersion":"0.1.10","srcDir":"src"},"source":{"url":"https://github.com/guzba/curly","rev":"a3fd81e3a79e51906a740b06306ebd55027fc943","date":"2023-05-29T01:00:58-05:00","path":"/nix/store/am0gd18zyfm6r115zaigxp00ymws86kf-curly","sha256":"00l824f8f0vfmiy7ch5v3x1k57l8psshv3nb61222rphmz5ayb5r","fetchLFS":false,"fetchSubmodules":true,"deepClone":false,"leaveDotGit":false,"method":"git"},"version":"0.1.10"},{"nimble":{"author":"Ryan Oldenburg","backend":"c","binDir":".","description":"Makes using libcurl efficiently easy","license":"MIT","requires":[{"name":"nim","range":">= 1.6.10"},{"name":"libcurl","range":">= 1.0.0"},{"name":"zippy","range":">= 0.10.6"},{"name":"waterpark","range":">= 0.1.3"},{"name":"webby","range":">= 0.1.7"}],"specialVersion":"0.1.9","srcDir":"src"},"source":{"url":"https://github.com/guzba/curly","rev":"79e84143492ebc7fc47affc3e9766237c410202b","date":"2023-05-17T22:56:10-05:00","path":"/nix/store/awsg9ls0b8g7bdj2dh3cp69y935sigdv-curly","sha256":"1isdc7mdk105ka3dv1lmrsfj8n2pvk4l1iwk4f64011a5ygn285h","fetchLFS":false,"fetchSubmodules":true,"deepClone":false,"leaveDotGit":false,"method":"git"},"version":"0.1.9"},{"nimble":{"author":"Ryan Oldenburg","backend":"c","binDir":".","description":"Makes using libcurl efficiently easy","license":"MIT","requires":[{"name":"nim","range":">= 1.6.10"},{"name":"libcurl","range":">= 1.0.0"},{"name":"zippy","range":">= 0.10.6"},{"name":"waterpark","range":">= 0.1.3"},{"name":"webby","range":">= 0.1.7"}],"specialVersion":"0.1.8","srcDir":"src"},"source":{"url":"https://github.com/guzba/curly","rev":"9f65e36e7dc47724db57851f9574fa2d4cc98ea6","date":"2023-05-17T15:56:25-05:00","path":"/nix/store/gd21ix29g51vfw1drzrfb2xvh8h04jfk-curly","sha256":"0j9zygm9w2sqdvbxw7k91n24ihr63shhwpz0wb3zif9yxkp47vz9","fetchLFS":false,"fetchSubmodules":true,"deepClone":false,"leaveDotGit":false,"method":"git"},"version":"0.1.8"},{"nimble":{"author":"Ryan Oldenburg","backend":"c","binDir":".","description":"Makes using libcurl efficiently easy","license":"MIT","requires":[{"name":"nim","range":">= 1.6.10"},{"name":"libcurl","range":">= 1.0.0"},{"name":"zippy","range":">= 0.10.6"},{"name":"waterpark","range":">= 0.1.3"},{"name":"webby","range":">= 0.1.7"}],"specialVersion":"0.1.7","srcDir":"src"},"source":{"url":"https://github.com/guzba/curly","rev":"c1bfcd9ea94ee653874ba297b9c659122999b79c","date":"2023-05-15T22:03:00-05:00","path":"/nix/store/3x3h40zyr279x4acc9wmdpwnj6ccv7pv-curly","sha256":"1xp6nvc7b0ryr6m3gfpzjdb5add7jnz3y0wmgwjkibxzvz3wbwyy","fetchLFS":false,"fetchSubmodules":true,"deepClone":false,"leaveDotGit":false,"method":"git"},"version":"0.1.7"},{"nimble":{"author":"Ryan Oldenburg","backend":"c","binDir":".","description":"Makes using libcurl efficiently easy","license":"MIT","requires":[{"name":"nim","range":">= 1.6.10"},{"name":"libcurl","range":">= 1.0.0"},{"name":"zippy","range":">= 0.10.6"},{"name":"waterpark","range":">= 0.1.3"},{"name":"webby","range":">= 0.1.7"}],"specialVersion":"0.1.6","srcDir":"src"},"source":{"url":"https://github.com/guzba/curly","rev":"351925e978c2e00c087368495b2649372b43cd15","date":"2023-04-04T13:55:49-05:00","path":"/nix/store/6bzi1kc4hmfsx8w83zarmg65pljwj37h-curly","sha256":"07ib75g598yhzxy29k9mv1ls1hp9k954rmikyz4cchhvqr4ryfih","fetchLFS":false,"fetchSubmodules":true,"deepClone":false,"leaveDotGit":false,"method":"git"},"version":"0.1.6"},{"nimble":{"author":"Ryan Oldenburg","backend":"c","binDir":".","description":"Makes using libcurl efficiently easy","license":"MIT","requires":[{"name":"nim","range":">= 1.6.10"},{"name":"libcurl","range":">= 1.0.0"},{"name":"zippy","range":">= 0.10.6"},{"name":"waterpark","range":">= 0.1.3"},{"name":"webby","range":">= 0.1.7"}],"specialVersion":"0.1.5","srcDir":"src"},"source":{"url":"https://github.com/guzba/curly","rev":"a582222a1c7489921de08a673a9e4135c1293d5b","date":"2023-02-12T15:30:03-06:00","path":"/nix/store/8jz9jzfqcp8ppwpi3z5ndd6m18ds6whc-curly","sha256":"0ncz8rz12hxmak99h5g2hy69xq0xq2ffm6b5qwjbb804knqd66j1","fetchLFS":false,"fetchSubmodules":true,"deepClone":false,"leaveDotGit":false,"method":"git"},"version":"0.1.5"},{"nimble":{"author":"Ryan Oldenburg","backend":"c","binDir":".","description":"Makes using libcurl efficiently easy","license":"MIT","requires":[{"name":"nim","range":">= 1.6.10"},{"name":"libcurl","range":">= 1.0.0"},{"name":"zippy","range":">= 0.10.6"},{"name":"waterpark","range":">= 0.1.3"},{"name":"webby","range":">= 0.1.7"}],"specialVersion":"0.1.4","srcDir":"src"},"source":{"url":"https://github.com/guzba/curly","rev":"4a742754e04485e95c01d0588adc8a7abb9d252d","date":"2023-02-10T17:19:00-06:00","path":"/nix/store/b9rvhqp3hd0000k7zv48wmab2ws1bih4-curly","sha256":"1sfld35scvd4jyzlhx11y3bf5k1lah4a6byzd56zqym6k30nsvw1","fetchLFS":false,"fetchSubmodules":true,"deepClone":false,"leaveDotGit":false,"method":"git"},"version":"0.1.4"},{"nimble":{"author":"Ryan Oldenburg","backend":"c","binDir":".","description":"Makes using libcurl efficiently easy","license":"MIT","requires":[{"name":"nim","range":">= 1.6.10"},{"name":"libcurl","range":">= 1.0.0"},{"name":"zippy","range":">= 0.10.6"},{"name":"waterpark","range":">= 0.1.3"},{"name":"webby","range":">= 0.1.7"}],"specialVersion":"0.1.3","srcDir":"src"},"source":{"url":"https://github.com/guzba/curly","rev":"e7a4c2c2482d22192c4f503f463e151ba8ce2706","date":"2023-02-10T16:22:01-06:00","path":"/nix/store/l1ljpawr7sysjx11a5hapfv8bdgb1kxl-curly","sha256":"14nrq9204csq8smdqcjfzkhmf1lciv6ar4i2mwzf4b1gm3jx1606","fetchLFS":false,"fetchSubmodules":true,"deepClone":false,"leaveDotGit":false,"method":"git"},"version":"0.1.3"},{"nimble":{"author":"Ryan Oldenburg","backend":"c","binDir":".","description":"Makes using libcurl efficiently easy","license":"MIT","requires":[{"name":"nim","range":">= 1.6.10"},{"name":"libcurl","range":">= 1.0.0"},{"name":"zippy","range":">= 0.10.6"},{"name":"waterpark","range":">= 0.1.1"},{"name":"webby","range":">= 0.1.3"}],"specialVersion":"0.1.2","srcDir":"src"},"source":{"url":"https://github.com/guzba/curly","rev":"af9c96c83184f5a79ca91578546eedb8af81707f","date":"2023-02-03T20:33:25-06:00","path":"/nix/store/x3fvwasrzfq62yd38q8f8ybwcxjax709-curly","sha256":"0nr076hhyhczjxlmclg7z6amx66lch4i24brf9bz99ivy04qh72r","fetchLFS":false,"fetchSubmodules":true,"deepClone":false,"leaveDotGit":false,"method":"git"},"version":"0.1.2"},{"nimble":{"author":"Ryan Oldenburg","backend":"c","binDir":".","description":"Makes using libcurl efficiently easy","license":"MIT","requires":[{"name":"nim","range":">= 1.6.10"},{"name":"libcurl","range":">= 1.0.0"},{"name":"zippy","range":">= 0.10.6"},{"name":"waterpark","range":">= 0.1.1"},{"name":"webby","range":">= 0.1.3"}],"specialVersion":"0.1.1","srcDir":"src"},"source":{"url":"https://github.com/guzba/curly","rev":"d0e09a7628fd1cf2e6ad041e3a49735ec52cdef6","date":"2023-01-12T00:47:42-06:00","path":"/nix/store/3klqvhriwsckhx0hsp13g2vk2m9anbci-curly","sha256":"0x2mb53rrx89604mhq4caxb7gi2xv7wcnay5n52cnajyig0rmd9c","fetchLFS":false,"fetchSubmodules":true,"deepClone":false,"leaveDotGit":false,"method":"git"},"version":"0.1.1"},{"nimble":{"author":"Ryan Oldenburg","backend":"c","binDir":".","description":"Makes using libcurl efficiently easy","license":"MIT","requires":[{"name":"nim","range":">= 1.6.10"},{"name":"libcurl","range":">= 1.0.0"},{"name":"zippy","range":">= 0.10.6"},{"name":"waterpark","range":">= 0.1.1"},{"name":"webby","range":">= 0.1.3"}],"specialVersion":"0.1.0","srcDir":"src"},"source":{"url":"https://github.com/guzba/curly","rev":"be1bb5f7fee3ad91f105071521b9058b996177cd","date":"2023-01-11T18:30:07-06:00","path":"/nix/store/dqz6c93rn3wzv94wip5jr3479p9ccylm-curly","sha256":"1wingx8nmxm87q23va6n372b8f4a1b2acfdd2aiw24nk106lajs3","fetchLFS":false,"fetchSubmodules":true,"deepClone":false,"leaveDotGit":false,"method":"git"},"version":"0.1.0"}]}