{"homepage":"https://github.com/NimAudio/nim-pugl","versions":[{"nimble":{"author":"Morgan Holly","backend":"c","binDir":".","description":"PUGL windowing bindings","license":"MIT","requires":[{"name":"nim","range":">= 2.0.2"}],"specialVersion":"0.1.0","srcDir":"src"},"source":{"url":"https://github.com/NimAudio/nim-pugl","rev":"446f775ec086020909bd3f284e00f814b287d18d","date":"2024-08-20T01:54:34-04:00","path":"/nix/store/2v7khxk3bmzq473nzfbb7qyb4bky5lff-nim-pugl","sha256":"00s0dkmp1k833pdf77nfw874dwancrc36xk58ms9yiqijyvdjdcq","fetchLFS":false,"fetchSubmodules":true,"deepClone":false,"leaveDotGit":false,"method":"git"},"version":"HEAD"}]}